<?xml version="1.0" encoding="UTF-8" standalone="no"?>
<datamodel-type xmlns="http://www.efaps.org/xsd" xmlns:xsi="http://www.w3.org/2001/XMLSchema-instance" xsi:schemaLocation="http://www.efaps.org/xsd http://www.efaps.org/xsd/eFaps_1.0.xsd">
    <uuid>bc0d6928-714c-4008-aa27-a2ee2d8723f3</uuid>
    <file-application>eFapsApp-Projects</file-application>
    
    <definition>
        <version-expression>(version==latest)</version-expression>
        <name>Projects_ProjectService2ServiceOrderOutbound</name>
        <parent>Projects_ProjectService2DocumentAbstract</parent>
        <attribute>
            <name>FromLink</name>
            <type>Link</type>
            <typelink>Projects_ProjectService</typelink>
            <sqltable>Projects_Project2DocumentAbstractSQLTable</sqltable>
            <sqlcolumn>FROMID</sqlcolumn>
        </attribute>
        <attribute>
            <name>ToLink</name>
            <type>Link</type>
            <typelink>Sales_ServiceOrderOutbound</typelink>
            <sqltable>Projects_Project2DocumentAbstractSQLTable</sqltable>
            <sqlcolumn>TOID</sqlcolumn>
        </attribute>
    </definition>
</datamodel-type>