<?xml version="1.0" encoding="UTF-8"?>




<ui-menu xmlns="http://www.efaps.org/xsd"
         xmlns:xsi="http://www.w3.org/2001/XMLSchema-instance"
         xsi:schemaLocation="http://www.efaps.org/xsd http://www.efaps.org/xsd/eFaps_1.0.xsd">
    <uuid>07300d4c-7336-4895-96c6-80d97889361f</uuid>
    <file-application>eFapsApp-Projects</file-application>
    
    <definition>
        <version-expression>(version==latest)</version-expression>
        <name>Projects_ProjectTree_Labels_Menu_Action</name>
        

        <childs>
            <child>Projects_ProjectTree_Labels_Menu_Action_AddExisting</child>
            <child>Projects_ProjectTree_Labels_Menu_Action_Disconnect</child>
        </childs>
    </definition>
</ui-menu>
